numpy_fn/__init__.py
numpy_fn/_numpy_fn.py
numpy_fn-1.0.0.dist-info/LICENSE
numpy_fn-1.0.0.dist-info/METADATA
numpy_fn-1.0.0.dist-info/WHEEL
numpy_fn-1.0.0.dist-info/top_level.txt
numpy_fn-1.0.0.dist-info/RECORD
