Metadata-Version: 2.1
Name: numpy-fn
Version: 1.0.0
Summary: A decorator for seamless numpy calculations from torch.tensor and pd.DataFrame.
Home-page: https://github.com/ywatanabe1989/numpy_fn
Author: ywatanabe1989
Author-email: ywata1989@gmail.com
License: MIT
Keywords: numpytorch,pandas
Platform: UNKNOWN
Classifier: Programming Language :: Python :: 3
Classifier: License :: OSI Approved :: MIT License
Requires-Python: >=3.6
License-File: LICENSE
Requires-Dist: numpy
Requires-Dist: torch
Requires-Dist: pandas
Requires-Dist: scipy
